{
  "date": "2026-07-01",
  "timezone": "Asia/Shanghai",
  "status": "validated_pending_commit_deploy_email",
  "article_quota": 2,
  "articles": [
    {
      "slug": "adjustable-cock-ring-guide",
      "title": "Adjustable Cock Ring Guide: Fit and Safety",
      "url": "https://shoplovanest.com/blog/adjustable-cock-ring-guide/",
      "primary_keywords": [
        "adjustable cock ring",
        "how tight should a cock ring be",
        "cock ring sizes",
        "silicone cock rings"
      ],
      "keyword_source": "output/merged_keyword_research_2026-06-25.csv rows: adjustable cock ring (Volume 1000), cock ring sizes (390), how tight should a cock ring be (390), silicone cock rings (390); mapping file places cock ring terms in the cock-ring buying guide family, expanded here as a distinct adjustable-fit intent without cannibalizing metal or vibrating ring pages.",
      "intent_cluster": "Couples accessories — adjustable fit, sizing, release, and safer beginner comparison intent"
    },
    {
      "slug": "realistic-male-masturbator-guide",
      "title": "Realistic Male Masturbator Guide: Care Checks",
      "url": "https://shoplovanest.com/blog/realistic-male-masturbator-guide/",
      "primary_keywords": [
        "realistic male masturbator",
        "best male masturbator",
        "male masturbator toy",
        "male masturbators"
      ],
      "keyword_source": "output/merged_keyword_research_2026-06-25.csv rows: realistic male masturbator (Volume 720), best male masturbator (4400), male masturbator toy (1300), male masturbators (9900); mapping file groups male masturbator terms under male wellness pages, expanded here for realistic sleeve care intent.",
      "intent_cluster": "Male wellness — realistic sleeve material, cleaning, drying, and private storage comparison intent"
    }
  ],
  "index_updated": true,
  "sitemap_updated": true,
  "generated_at": "2026-07-01T08:56:41.344049+08:00",
  "local_validation": {
    "status": "pass",
    "title_meta_h1_gtag": true,
    "word_count_1000_plus": true,
    "readability_natural_english": true,
    "topic_specific_depth": true,
    "quick_answer": true,
    "red_flags": true,
    "faqpage_jsonld": true,
    "authority_refs": true,
    "internal_product_links": true,
    "image_seo_metadata": true,
    "sitemap_image_metadata": true,
    "quality_score_min": 100,
    "articles": {
      "adjustable-cock-ring-guide": {
        "title_length": 42,
        "meta_length": 130,
        "word_count": 1200,
        "quality_score": 100
      },
      "realistic-male-masturbator-guide": {
        "title_length": 45,
        "meta_length": 132,
        "word_count": 1081,
        "quality_score": 100
      }
    }
  },
  "image_generation": {
    "status": "pass",
    "model": "opus-image-1.5 via custom Responses API image_generation tool",
    "files": [
      "upload/blog/assets/adjustable-cock-ring-guide-opus-cover.png",
      "upload/blog/assets/realistic-male-masturbator-guide-opus-cover.png"
    ]
  }
}